squirrel/__init__.py
squirrel/__main__.py
squirrel/dev_utils.py
squirrel/exceptions.py
squirrel/plugin.py
squirrel/squirrel.py
squirrel/vars.py
squirrel/xml.py
squirrel/argparsers/__init__.py
squirrel/argparsers/parsers.py
squirrel/argparsers/setup.py
squirrel/commands/__init__.py
squirrel/commands/data.py
squirrel/commands/init.py
squirrel/commands/overview.py
squirrel/commands/set.py
squirrel/commands/watch.py
squirrel/plugins/__init__.py
squirrel/plugins/example_plugin/__init__.py
squirrel/plugins/example_plugin/example_plugin.py
squirrel/plugins/texcount/__init__.py
squirrel/plugins/texcount/texcount.py
squirrel/plugins/text/__init__.py
squirrel/plugins/text/text.py
squirrel_writer-0.0.4.dist-info/LICENSE
squirrel_writer-0.0.4.dist-info/METADATA
squirrel_writer-0.0.4.dist-info/WHEEL
squirrel_writer-0.0.4.dist-info/entry_points.txt
squirrel_writer-0.0.4.dist-info/top_level.txt
squirrel_writer-0.0.4.dist-info/RECORD
