Metadata-Version: 2.1
Name: squirrel-writer
Version: 0.0.4
Summary: A command line program to track writing progress
Home-page: https://github.com/squirrel-writer/squirrel
Author: Mohieddine Drissi
Author-email: m.drissi@protonmail.com
License: UNKNOWN
Platform: UNKNOWN
Classifier: Programming Language :: Python :: 3.8
Classifier: Programming Language :: Python :: 3.9
Classifier: Programming Language :: Python :: 3.10
Classifier: License :: OSI Approved :: GNU General Public License v3 (GPLv3)
Classifier: Development Status :: 2 - Pre-Alpha
Requires-Python: >=3.8
License-File: LICENSE
Requires-Dist: commonmark (==0.9.1)
Requires-Dist: daemonize (==2.5.0)
Requires-Dist: python-dateutil (==2.8.2)
Requires-Dist: pyyaml (==6.0)
Requires-Dist: rich (==11.2.0)
Requires-Dist: watchdog (==2.1.6)
Requires-Dist: six (==1.16.0) ; python_version >= "2.7" and python_version not in "3.0, 3.1, 3.2, 3.3"
Requires-Dist: colorama (==0.4.4) ; python_version >= "2.7" and python_version not in "3.0, 3.1, 3.2, 3.3, 3.4"
Requires-Dist: pygments (==2.11.2) ; python_version >= "3.5"
Provides-Extra: dev
Requires-Dist: appdirs (==1.4.4) ; extra == 'dev'
Requires-Dist: autopep8 (==1.6.0) ; extra == 'dev'
Requires-Dist: cached-property (==1.5.2) ; extra == 'dev'
Requires-Dist: cerberus (==1.3.4) ; extra == 'dev'
Requires-Dist: certifi (==2021.10.8) ; extra == 'dev'
Requires-Dist: cffi (==1.15.0) ; extra == 'dev'
Requires-Dist: check-manifest (==0.47) ; extra == 'dev'
Requires-Dist: codespell (==2.1.0) ; extra == 'dev'
Requires-Dist: coverage (==6.3.1) ; extra == 'dev'
Requires-Dist: distlib (==0.3.4) ; extra == 'dev'
Requires-Dist: flake8 (==4.0.1) ; extra == 'dev'
Requires-Dist: iniconfig (==1.1.1) ; extra == 'dev'
Requires-Dist: mccabe (==0.6.1) ; extra == 'dev'
Requires-Dist: nodeenv (==1.6.0) ; extra == 'dev'
Requires-Dist: orderedmultidict (==1.0.1) ; extra == 'dev'
Requires-Dist: pathspec (==0.9.0) ; extra == 'dev'
Requires-Dist: pep517 (==0.12.0) ; extra == 'dev'
Requires-Dist: pipenv-setup (==3.1.4) ; extra == 'dev'
Requires-Dist: pipfile (==0.0.2) ; extra == 'dev'
Requires-Dist: pkginfo (==1.8.2) ; extra == 'dev'
Requires-Dist: pre-commit (==2.17.0) ; extra == 'dev'
Requires-Dist: pycparser (==2.21) ; extra == 'dev'
Requires-Dist: pytest (==7.0.1) ; extra == 'dev'
Requires-Dist: pytest-mock (==3.7.0) ; extra == 'dev'
Requires-Dist: python-dateutil (==2.8.2) ; extra == 'dev'
Requires-Dist: pyyaml (==6.0) ; extra == 'dev'
Requires-Dist: regex (==2022.1.18) ; extra == 'dev'
Requires-Dist: requests-toolbelt (==0.9.1) ; extra == 'dev'
Requires-Dist: tox (==3.24.5) ; extra == 'dev'
Requires-Dist: twine (==3.8.0) ; extra == 'dev'
Requires-Dist: webencodings (==0.5.1) ; extra == 'dev'
Requires-Dist: yelp-gprof2dot (==1.2.0) ; extra == 'dev'
Requires-Dist: cfgv (==3.3.1) ; (python_full_version >= "3.6.1") and extra == 'dev'
Requires-Dist: plette[validation] (==0.2.3) ; (python_version >= "2.6" and python_version not in "3.0, 3.1, 3.2, 3.3") and extra == 'dev'
Requires-Dist: toml (==0.10.2) ; (python_version >= "2.6" and python_version not in "3.0, 3.1, 3.2, 3.3") and extra == 'dev'
Requires-Dist: packaging (==20.9) ; (python_version >= "2.7" and python_version not in "3.0, 3.1, 3.2, 3.3") and extra == 'dev'
Requires-Dist: pyflakes (==2.4.0) ; (python_version >= "2.7" and python_version not in "3.0, 3.1, 3.2, 3.3") and extra == 'dev'
Requires-Dist: six (==1.16.0) ; (python_version >= "2.7" and python_version not in "3.0, 3.1, 3.2, 3.3") and extra == 'dev'
Requires-Dist: tqdm (==4.62.3) ; (python_version >= "2.7" and python_version not in "3.0, 3.1, 3.2, 3.3") and extra == 'dev'
Requires-Dist: vistir (==0.5.2) ; (python_version >= "2.7" and python_version not in "3.0, 3.1, 3.2, 3.3") and extra == 'dev'
Requires-Dist: attrs (==21.4.0) ; (python_version >= "2.7" and python_version not in "3.0, 3.1, 3.2, 3.3, 3.4") and extra == 'dev'
Requires-Dist: chardet (==4.0.0) ; (python_version >= "2.7" and python_version not in "3.0, 3.1, 3.2, 3.3, 3.4") and extra == 'dev'
Requires-Dist: colorama (==0.4.4) ; (python_version >= "2.7" and python_version not in "3.0, 3.1, 3.2, 3.3, 3.4") and extra == 'dev'
Requires-Dist: docutils (==0.18.1) ; (python_version >= "2.7" and python_version not in "3.0, 3.1, 3.2, 3.3, 3.4") and extra == 'dev'
Requires-Dist: py (==1.11.0) ; (python_version >= "2.7" and python_version not in "3.0, 3.1, 3.2, 3.3, 3.4") and extra == 'dev'
Requires-Dist: pycodestyle (==2.8.0) ; (python_version >= "2.7" and python_version not in "3.0, 3.1, 3.2, 3.3, 3.4") and extra == 'dev'
Requires-Dist: virtualenv (==20.13.1) ; (python_version >= "2.7" and python_version not in "3.0, 3.1, 3.2, 3.3, 3.4") and extra == 'dev'
Requires-Dist: wheel (==0.37.1) ; (python_version >= "2.7" and python_version not in "3.0, 3.1, 3.2, 3.3, 3.4") and extra == 'dev'
Requires-Dist: urllib3 (==1.26.8) ; (python_version >= "2.7" and python_version not in "3.0, 3.1, 3.2, 3.3, 3.4" and python_version < "4") and extra == 'dev'
Requires-Dist: requests (==2.27.1) ; (python_version >= "2.7" and python_version not in "3.0, 3.1, 3.2, 3.3, 3.4, 3.5") and extra == 'dev'
Requires-Dist: charset-normalizer (==2.0.12) ; (python_version >= "3") and extra == 'dev'
Requires-Dist: idna (==3.3) ; (python_version >= "3") and extra == 'dev'
Requires-Dist: pygments (==2.11.2) ; (python_version >= "3.5") and extra == 'dev'
Requires-Dist: black (==19.10b0) ; (python_version >= "3.6") and extra == 'dev'
Requires-Dist: bleach (==4.1.0) ; (python_version >= "3.6") and extra == 'dev'
Requires-Dist: build (==0.7.0) ; (python_version >= "3.6") and extra == 'dev'
Requires-Dist: click (==8.0.3) ; (python_version >= "3.6") and extra == 'dev'
Requires-Dist: cryptography (==36.0.1) ; (python_version >= "3.6") and extra == 'dev'
Requires-Dist: pip-shims (==0.6.0) ; (python_version >= "3.6") and extra == 'dev'
Requires-Dist: pluggy (==1.0.0) ; (python_version >= "3.6") and extra == 'dev'
Requires-Dist: pyparsing (==3.0.7) ; (python_version >= "3.6") and extra == 'dev'
Requires-Dist: readme-renderer (==32.0) ; (python_version >= "3.6") and extra == 'dev'
Requires-Dist: requirementslib (==1.6.1) ; (python_version >= "3.6") and extra == 'dev'
Requires-Dist: typed-ast (==1.5.2) ; (python_version >= "3.6") and extra == 'dev'
Requires-Dist: tomlkit (==0.9.2) ; (python_version >= "3.6" and python_version < "4") and extra == 'dev'
Requires-Dist: filelock (==3.5.1) ; (python_version >= "3.7") and extra == 'dev'
Requires-Dist: identify (==2.4.10) ; (python_version >= "3.7") and extra == 'dev'
Requires-Dist: importlib-metadata (==4.11.1) ; (python_version >= "3.7") and extra == 'dev'
Requires-Dist: keyring (==23.5.0) ; (python_version >= "3.7") and extra == 'dev'
Requires-Dist: pip (==22.0.3) ; (python_version >= "3.7") and extra == 'dev'
Requires-Dist: platformdirs (==2.5.0) ; (python_version >= "3.7") and extra == 'dev'
Requires-Dist: rfc3986 (==2.0.0) ; (python_version >= "3.7") and extra == 'dev'
Requires-Dist: setuptools (==60.9.2) ; (python_version >= "3.7") and extra == 'dev'
Requires-Dist: tomli (==2.0.1) ; (python_version >= "3.7") and extra == 'dev'
Requires-Dist: zipp (==3.7.0) ; (python_version >= "3.7") and extra == 'dev'
Requires-Dist: jeepney (==0.7.1) ; (sys_platform == "linux") and extra == 'dev'
Requires-Dist: secretstorage (==3.3.1) ; (sys_platform == "linux") and extra == 'dev'
